romanclass/__init__.py
romanclass/romanclass.py
romanclass-1.2.3.dist-info/METADATA
romanclass-1.2.3.dist-info/WHEEL
romanclass-1.2.3.dist-info/top_level.txt
romanclass-1.2.3.dist-info/RECORD
