Metadata-Version: 2.2
Name: romanclass
Version: 1.2.3
Summary: Binary int class using Roman numerals for input and output
Author: Vernon Cole
Author-email: vernondcole@gmail.com
License: MIT
Project-URL: repository, https://launchpad.net/romanclass
Project-URL: documentation, https://git.launchpad.net/romanclass/tree/README.rst
Keywords: Roman numbers,romanclass,emulate int
Classifier: Development Status :: 5 - Production/Stable
Classifier: Intended Audience :: Developers
Classifier: Intended Audience :: Education
Classifier: License :: OSI Approved :: MIT License
Classifier: Programming Language :: Python
Classifier: Natural Language :: Latin
Classifier: Operating System :: OS Independent
Classifier: Topic :: Software Development
Classifier: Topic :: Software Development :: Libraries :: Python Modules
